{"Nodes": {"DistributedObjectBase___init__": {"name": "DistributedObjectBase", "cat": "Panda3D,direct,DistributedObjectBase", "extraAttr": {"py": "Call(Attribute({self}, DistributedObjectBase), [cr])"}, "out": ["Next", "value"], "in": [{"name": "Call", "type": "In"}, {"name": "self", "type": "In"}, {"name": "cr", "type": "In"}]}, "DistributedObjectBase_getLocation": {"name": "getLocation", "cat": "Panda3D,direct,DistributedObjectBase", "extraAttr": {"py": "Call(Attribute({self}, getLocation), [])"}, "out": ["Next", "value"], "in": [{"name": "Call", "type": "In"}, {"name": "self", "type": "In"}]}, "DistributedObjectBase_handleChildArrive": {"name": "handleChildArrive", "cat": "Panda3D,direct,DistributedObjectBase", "extraAttr": {"py": "Call(Attribute({self}, handleChildArrive), [childObj,zoneId])"}, "out": ["Next", "value"], "in": [{"name": "Call", "type": "In"}, {"name": "self", "type": "In"}, {"name": "childObj", "type": "In"}, {"name": "zoneId", "type": "In"}]}, "DistributedObjectBase_handleChildArriveZone": {"name": "handleChildArriveZone", "cat": "Panda3D,direct,DistributedObjectBase", "extraAttr": {"py": "Call(Attribute({self}, handleChildArriveZone), [childObj,zoneId])"}, "out": ["Next", "value"], "in": [{"name": "Call", "type": "In"}, {"name": "self", "type": "In"}, {"name": "childObj", "type": "In"}, {"name": "zoneId", "type": "In"}]}, "DistributedObjectBase_handleChildLeave": {"name": "handleChildLeave", "cat": "Panda3D,direct,DistributedObjectBase", "extraAttr": {"py": "Call(Attribute({self}, handleChildLeave), [childObj,zoneId])"}, "out": ["Next", "value"], "in": [{"name": "Call", "type": "In"}, {"name": "self", "type": "In"}, {"name": "childObj", "type": "In"}, {"name": "zoneId", "type": "In"}]}, "DistributedObjectBase_handleChildLeaveZone": {"name": "handleChildLeaveZone", "cat": "Panda3D,direct,DistributedObjectBase", "extraAttr": {"py": "Call(Attribute({self}, handleChildLeaveZone), [childObj,zoneId])"}, "out": ["Next", "value"], "in": [{"name": "Call", "type": "In"}, {"name": "self", "type": "In"}, {"name": "childObj", "type": "In"}, {"name": "zoneId", "type": "In"}]}, "DistributedObjectBase_handleQueryObjectChildrenLocalDone": {"name": "handleQueryObjectChildrenLocalDone", "cat": "Panda3D,direct,DistributedObjectBase", "extraAttr": {"py": "Call(Attribute({self}, handleQueryObjectChildrenLocalDone), [context])"}, "out": ["Next", "value"], "in": [{"name": "Call", "type": "In"}, {"name": "self", "type": "In"}, {"name": "context", "type": "In"}]}, "DistributedObjectBase_getParentObj": {"name": "getParentObj", "cat": "Panda3D,direct,DistributedObjectBase", "extraAttr": {"py": "Call(Attribute({self}, getParentObj), [])"}, "out": ["Next", "value"], "in": [{"name": "Call", "type": "In"}, {"name": "self", "type": "In"}]}, "DistributedObjectBase_hasParentingRules": {"name": "hasParentingRules", "cat": "Panda3D,direct,DistributedObjectBase", "extraAttr": {"py": "Call(Attribute({self}, hasParentingRules), [])"}, "out": ["Next", "value"], "in": [{"name": "Call", "type": "In"}, {"name": "self", "type": "In"}]}, "DistributedObjectBase_delete": {"name": "delete", "cat": "Panda3D,direct,DistributedObjectBase", "extraAttr": {"py": "Call(Attribute({self}, delete), [])"}, "out": ["Next", "value"], "in": [{"name": "Call", "type": "In"}, {"name": "self", "type": "In"}]}}}