{"Nodes": {"ShadowCaster___init__": {"name": "ShadowCaster", "cat": "Panda3D,direct,ShadowCaster", "extraAttr": {"py": "Call(Attribute({self}, ShadowCaster), [lightPath,objectPath,filmX,filmY])"}, "out": ["Next", "value"], "in": [{"name": "Call", "type": "In"}, {"name": "self", "type": "In"}, {"name": "lightPath", "type": "In"}, {"name": "objectPath", "type": "In"}, {"name": "filmX", "type": "In"}, {"name": "filmY", "type": "In"}]}, "ShadowCaster_setGround": {"name": "setGround", "cat": "Panda3D,direct,ShadowCaster", "extraAttr": {"py": "Call(Attribute({self}, setGround), [groundPath])"}, "out": ["Next", "value"], "in": [{"name": "Call", "type": "In"}, {"name": "self", "type": "In"}, {"name": "groundPath", "type": "In"}]}, "ShadowCaster_clear": {"name": "clear", "cat": "Panda3D,direct,ShadowCaster", "extraAttr": {"py": "Call(Attribute({self}, clear), [])"}, "out": ["Next", "value"], "in": [{"name": "Call", "type": "In"}, {"name": "self", "type": "In"}]}, "avatarShadow": {"name": "avatarShadow", "cat": "Panda3D,direct", "extraAttr": {"py": ["Call(avatarShadow, [])"]}, "out": ["Next", "value"], "in": [{"name": "Call", "type": "In"}]}, "piratesAvatarShadow": {"name": "piratesAvatarShadow", "cat": "Panda3D,direct", "extraAttr": {"py": ["Call(piratesAvatarShadow, [])"]}, "out": ["Next", "value"], "in": [{"name": "Call", "type": "In"}]}, "arbitraryShadow": {"name": "arbitraryShadow", "cat": "Panda3D,direct", "extraAttr": {"py": ["Call(arbitraryShadow, [node])"]}, "out": ["Next", "value"], "in": [{"name": "Call", "type": "In"}, {"name": "node", "type": "In"}]}}}