{"Nodes": {"ParticleFloorTest___init__": {"name": "ParticleFloorTest", "cat": "Panda3D,direct,ParticleFloorTest", "extraAttr": {"py": "Call(Attribute({self}, ParticleFloorTest), [])"}, "out": ["Next", "value"], "in": [{"name": "Call", "type": "In"}, {"name": "self", "type": "In"}]}, "ParticleFloorTest_start": {"name": "start", "cat": "Panda3D,direct,ParticleFloorTest", "extraAttr": {"py": "Call(Attribute({self}, start), [])"}, "out": ["Next", "value"], "in": [{"name": "Call", "type": "In"}, {"name": "self", "type": "In"}]}}}