{"Nodes": {"CurveEditor___init__": {"name": "CurveEditor", "cat": "Panda3D,direct,CurveEditor", "extraAttr": {"py": "Call(Attribute({self}, CurveEditor), [editor])"}, "out": ["Next", "value"], "in": [{"name": "Call", "type": "In"}, {"name": "self", "type": "In"}, {"name": "editor", "type": "In"}]}, "CurveEditor_createCurve": {"name": "createCurve", "cat": "Panda3D,direct,CurveEditor", "extraAttr": {"py": "Call(Attribute({self}, createCurve), [])"}, "out": ["Next", "value"], "in": [{"name": "Call", "type": "In"}, {"name": "self", "type": "In"}]}, "CurveEditor_editCurve": {"name": "editCurve", "cat": "Panda3D,direct,CurveEditor", "extraAttr": {"py": "Call(Attribute({self}, editCurve), [task])"}, "out": ["Next", "value"], "in": [{"name": "Call", "type": "In"}, {"name": "self", "type": "In"}, {"name": "task", "type": "In"}]}, "CurveEditor_onControlerDelete": {"name": "onControlerDelete", "cat": "Panda3D,direct,CurveEditor", "extraAttr": {"py": "Call(Attribute({self}, onControlerDelete), [])"}, "out": ["Next", "value"], "in": [{"name": "Call", "type": "In"}, {"name": "self", "type": "In"}]}, "CurveEditor_ropeUpdate": {"name": "ropeUpdate", "cat": "Panda3D,direct,CurveEditor", "extraAttr": {"py": "Call(Attribute({self}, ropeUpdate), [curve])"}, "out": ["Next", "value"], "in": [{"name": "Call", "type": "In"}, {"name": "self", "type": "In"}, {"name": "curve", "type": "In"}]}, "CurveEditor_onBaseMode": {"name": "onBaseMode", "cat": "Panda3D,direct,CurveEditor", "extraAttr": {"py": "Call(Attribute({self}, onBaseMode), [])"}, "out": ["Next", "value"], "in": [{"name": "Call", "type": "In"}, {"name": "self", "type": "In"}]}, "CurveEditor_updateScene": {"name": "updateScene", "cat": "Panda3D,direct,CurveEditor", "extraAttr": {"py": "Call(Attribute({self}, updateScene), [])"}, "out": ["Next", "value"], "in": [{"name": "Call", "type": "In"}, {"name": "self", "type": "In"}]}, "CurveEditor_doneEdit": {"name": "doneEdit", "cat": "Panda3D,direct,CurveEditor", "extraAttr": {"py": "Call(Attribute({self}, doneEdit), [])"}, "out": ["Next", "value"], "in": [{"name": "Call", "type": "In"}, {"name": "self", "type": "In"}]}, "CurveEditor_createControler": {"name": "createControler", "cat": "Panda3D,direct,CurveEditor", "extraAttr": {"py": "Call(Attribute({self}, createControler), [x,y])"}, "out": ["Next", "value"], "in": [{"name": "Call", "type": "In"}, {"name": "self", "type": "In"}, {"name": "x", "type": "In"}, {"name": "y", "type": "In"}]}}}