{"Nodes": {"egg2bam": {"name": "egg2bam", "cat": "Panda3D,direct", "extraAttr": {"py": ["Call(egg2bam, [_build_cmd,srcpath,dstpath])"]}, "out": ["Next", "value"], "in": [{"name": "Call", "type": "In"}, {"name": "_build_cmd", "type": "In"}, {"name": "srcpath", "type": "In"}, {"name": "dstpath", "type": "In"}]}, "build_apps_initialize_options": {"name": "initialize_options", "cat": "Panda3D,direct,build_apps", "extraAttr": {"py": "Call(Attribute({self}, initialize_options), [])"}, "out": ["Next", "value"], "in": [{"name": "Call", "type": "In"}, {"name": "self", "type": "In"}]}, "build_apps_finalize_options": {"name": "finalize_options", "cat": "Panda3D,direct,build_apps", "extraAttr": {"py": "Call(Attribute({self}, finalize_options), [])"}, "out": ["Next", "value"], "in": [{"name": "Call", "type": "In"}, {"name": "self", "type": "In"}]}, "build_apps_run": {"name": "run", "cat": "Panda3D,direct,build_apps", "extraAttr": {"py": "Call(Attribute({self}, run), [])"}, "out": ["Next", "value"], "in": [{"name": "Call", "type": "In"}, {"name": "self", "type": "In"}]}, "build_apps_download_wheels": {"name": "download_wheels", "cat": "Panda3D,direct,build_apps", "extraAttr": {"py": "Call(Attribute({self}, download_wheels), [platform])"}, "out": ["Next", "value"], "in": [{"name": "Call", "type": "In"}, {"name": "self", "type": "In"}, {"name": "platform", "type": "In"}]}, "build_apps_update_pe_resources": {"name": "update_pe_resources", "cat": "Panda3D,direct,build_apps", "extraAttr": {"py": "Call(Attribute({self}, update_pe_resources), [appname,runtime])"}, "out": ["Next", "value"], "in": [{"name": "Call", "type": "In"}, {"name": "self", "type": "In"}, {"name": "appname", "type": "In"}, {"name": "runtime", "type": "In"}]}, "build_apps_bundle_macos_app": {"name": "bundle_macos_app", "cat": "Panda3D,direct,build_apps", "extraAttr": {"py": "Call(Attribute({self}, bundle_macos_app), [builddir])"}, "out": ["Next", "value"], "in": [{"name": "Call", "type": "In"}, {"name": "self", "type": "In"}, {"name": "builddir", "type": "In"}]}, "build_apps_build_runtimes": {"name": "build_runtimes", "cat": "Panda3D,direct,build_apps", "extraAttr": {"py": "Call(Attribute({self}, build_runtimes), [platform,use_wheels])"}, "out": ["Next", "value"], "in": [{"name": "Call", "type": "In"}, {"name": "self", "type": "In"}, {"name": "platform", "type": "In"}, {"name": "use_wheels", "type": "In"}]}, "build_apps_add_dependency": {"name": "add_dependency", "cat": "Panda3D,direct,build_apps", "extraAttr": {"py": "Call(Attribute({self}, add_dependency), [name,target_dir,search_path,referenced_by])"}, "out": ["Next", "value"], "in": [{"name": "Call", "type": "In"}, {"name": "self", "type": "In"}, {"name": "name", "type": "In"}, {"name": "target_dir", "type": "In"}, {"name": "search_path", "type": "In"}, {"name": "referenced_by", "type": "In"}]}, "build_apps_copy": {"name": "copy", "cat": "Panda3D,direct,build_apps", "extraAttr": {"py": "Call(Attribute({self}, copy), [source_path,target_path])"}, "out": ["Next", "value"], "in": [{"name": "Call", "type": "In"}, {"name": "self", "type": "In"}, {"name": "source_path", "type": "In"}, {"name": "target_path", "type": "In"}]}, "build_apps_copy_with_dependencies": {"name": "copy_with_dependencies", "cat": "Panda3D,direct,build_apps", "extraAttr": {"py": "Call(Attribute({self}, copy_with_dependencies), [source_path,target_path,search_path])"}, "out": ["Next", "value"], "in": [{"name": "Call", "type": "In"}, {"name": "self", "type": "In"}, {"name": "source_path", "type": "In"}, {"name": "target_path", "type": "In"}, {"name": "search_path", "type": "In"}]}, "build_apps_copy_dependencies": {"name": "copy_dependencies", "cat": "Panda3D,direct,build_apps", "extraAttr": {"py": "Call(Attribute({self}, copy_dependencies), [target_path,target_dir,search_path,referenced_by])"}, "out": ["Next", "value"], "in": [{"name": "Call", "type": "In"}, {"name": "self", "type": "In"}, {"name": "target_path", "type": "In"}, {"name": "target_dir", "type": "In"}, {"name": "search_path", "type": "In"}, {"name": "referenced_by", "type": "In"}]}, "build_apps_expand_path": {"name": "expand_path", "cat": "Panda3D,direct,build_apps", "extraAttr": {"py": "Call(Attribute({self}, expand_path), [path,platform])"}, "out": ["Next", "value"], "in": [{"name": "Call", "type": "In"}, {"name": "self", "type": "In"}, {"name": "path", "type": "In"}, {"name": "platform", "type": "In"}]}, "bdist_apps_initialize_options": {"name": "initialize_options", "cat": "Panda3D,direct,bdist_apps", "extraAttr": {"py": "Call(Attribute({self}, initialize_options), [])"}, "out": ["Next", "value"], "in": [{"name": "Call", "type": "In"}, {"name": "self", "type": "In"}]}, "bdist_apps_finalize_options": {"name": "finalize_options", "cat": "Panda3D,direct,bdist_apps", "extraAttr": {"py": "Call(Attribute({self}, finalize_options), [])"}, "out": ["Next", "value"], "in": [{"name": "Call", "type": "In"}, {"name": "self", "type": "In"}]}, "bdist_apps_create_zip": {"name": "create_zip", "cat": "Panda3D,direct,bdist_apps", "extraAttr": {"py": "Call(Attribute({self}, create_zip), [basename,build_dir])"}, "out": ["Next", "value"], "in": [{"name": "Call", "type": "In"}, {"name": "self", "type": "In"}, {"name": "basename", "type": "In"}, {"name": "build_dir", "type": "In"}]}, "bdist_apps_create_tarball": {"name": "create_tarball", "cat": "Panda3D,direct,bdist_apps", "extraAttr": {"py": "Call(Attribute({self}, create_tarball), [basename,build_dir,tar_compression])"}, "out": ["Next", "value"], "in": [{"name": "Call", "type": "In"}, {"name": "self", "type": "In"}, {"name": "basename", "type": "In"}, {"name": "build_dir", "type": "In"}, {"name": "tar_compression", "type": "In"}]}, "bdist_apps_create_nsis": {"name": "create_nsis", "cat": "Panda3D,direct,bdist_apps", "extraAttr": {"py": "Call(Attribute({self}, create_nsis), [basename,build_dir,is_64bit])"}, "out": ["Next", "value"], "in": [{"name": "Call", "type": "In"}, {"name": "self", "type": "In"}, {"name": "basename", "type": "In"}, {"name": "build_dir", "type": "In"}, {"name": "is_64bit", "type": "In"}]}, "bdist_apps_run": {"name": "run", "cat": "Panda3D,direct,bdist_apps", "extraAttr": {"py": "Call(Attribute({self}, run), [])"}, "out": ["Next", "value"], "in": [{"name": "Call", "type": "In"}, {"name": "self", "type": "In"}]}, "finalize_distribution_options": {"name": "finalize_distribution_options", "cat": "Panda3D,direct", "extraAttr": {"py": ["Call(finalize_distribution_options, [dist])"]}, "out": ["Next", "value"], "in": [{"name": "Call", "type": "In"}, {"name": "dist", "type": "In"}]}}}