{"Nodes": {"DirectLight___init__": {"name": "DirectLight", "cat": "Panda3D,direct,DirectLight", "extraAttr": {"py": "Call(Attribute({self}, DirectLight), [light,parent])"}, "out": ["Next", "value"], "in": [{"name": "Call", "type": "In"}, {"name": "self", "type": "In"}, {"name": "light", "type": "In"}, {"name": "parent", "type": "In"}]}, "DirectLight_getName": {"name": "getName", "cat": "Panda3D,direct,DirectLight", "extraAttr": {"py": "Call(Attribute({self}, getName), [])"}, "out": ["Next", "value"], "in": [{"name": "Call", "type": "In"}, {"name": "self", "type": "In"}]}, "DirectLight_getLight": {"name": "getLight", "cat": "Panda3D,direct,DirectLight", "extraAttr": {"py": "Call(Attribute({self}, getLight), [])"}, "out": ["Next", "value"], "in": [{"name": "Call", "type": "In"}, {"name": "self", "type": "In"}]}, "DirectLights___init__": {"name": "DirectLights", "cat": "Panda3D,direct,DirectLights", "extraAttr": {"py": "Call(Attribute({self}, DirectLights), [parent])"}, "out": ["Next", "value"], "in": [{"name": "Call", "type": "In"}, {"name": "self", "type": "In"}, {"name": "parent", "type": "In"}]}, "DirectLights___getitem__": {"name": "__getitem__", "cat": "Panda3D,direct,DirectLights", "extraAttr": {"py": "Call(Attribute({self}, __getitem__), [name])"}, "out": ["Next", "value"], "in": [{"name": "Call", "type": "In"}, {"name": "self", "type": "In"}, {"name": "name", "type": "In"}]}, "DirectLights___len__": {"name": "__len__", "cat": "Panda3D,direct,DirectLights", "extraAttr": {"py": "Call(Attribute({self}, __len__), [])"}, "out": ["Next", "value"], "in": [{"name": "Call", "type": "In"}, {"name": "self", "type": "In"}]}, "DirectLights_delete": {"name": "delete", "cat": "Panda3D,direct,DirectLights", "extraAttr": {"py": "Call(Attribute({self}, delete), [light])"}, "out": ["Next", "value"], "in": [{"name": "Call", "type": "In"}, {"name": "self", "type": "In"}, {"name": "light", "type": "In"}]}, "DirectLights_deleteAll": {"name": "deleteAll", "cat": "Panda3D,direct,DirectLights", "extraAttr": {"py": "Call(Attribute({self}, deleteAll), [])"}, "out": ["Next", "value"], "in": [{"name": "Call", "type": "In"}, {"name": "self", "type": "In"}]}, "DirectLights_asList": {"name": "asList", "cat": "Panda3D,direct,DirectLights", "extraAttr": {"py": "Call(Attribute({self}, asList), [])"}, "out": ["Next", "value"], "in": [{"name": "Call", "type": "In"}, {"name": "self", "type": "In"}]}, "DirectLights_getNameList": {"name": "getNameList", "cat": "Panda3D,direct,DirectLights", "extraAttr": {"py": "Call(Attribute({self}, getNameList), [])"}, "out": ["Next", "value"], "in": [{"name": "Call", "type": "In"}, {"name": "self", "type": "In"}]}, "DirectLights_create": {"name": "create", "cat": "Panda3D,direct,DirectLights", "extraAttr": {"py": "Call(Attribute({self}, create), [type])"}, "out": ["Next", "value"], "in": [{"name": "Call", "type": "In"}, {"name": "self", "type": "In"}, {"name": "type", "type": "In"}]}, "DirectLights_createDefaultLights": {"name": "createDefaultLights", "cat": "Panda3D,direct,DirectLights", "extraAttr": {"py": "Call(Attribute({self}, createDefaultLights), [])"}, "out": ["Next", "value"], "in": [{"name": "Call", "type": "In"}, {"name": "self", "type": "In"}]}, "DirectLights_allOn": {"name": "allOn", "cat": "Panda3D,direct,DirectLights", "extraAttr": {"py": "Call(Attribute({self}, allOn), [])"}, "out": ["Next", "value"], "in": [{"name": "Call", "type": "In"}, {"name": "self", "type": "In"}]}, "DirectLights_allOff": {"name": "allOff", "cat": "Panda3D,direct,DirectLights", "extraAttr": {"py": "Call(Attribute({self}, allOff), [])"}, "out": ["Next", "value"], "in": [{"name": "Call", "type": "In"}, {"name": "self", "type": "In"}]}, "DirectLights_toggle": {"name": "toggle", "cat": "Panda3D,direct,DirectLights", "extraAttr": {"py": "Call(Attribute({self}, toggle), [])"}, "out": ["Next", "value"], "in": [{"name": "Call", "type": "In"}, {"name": "self", "type": "In"}]}, "DirectLights_setOn": {"name": "setOn", "cat": "Panda3D,direct,DirectLights", "extraAttr": {"py": "Call(Attribute({self}, setOn), [directLight])"}, "out": ["Next", "value"], "in": [{"name": "Call", "type": "In"}, {"name": "self", "type": "In"}, {"name": "directLight", "type": "In"}]}, "DirectLights_setOff": {"name": "setOff", "cat": "Panda3D,direct,DirectLights", "extraAttr": {"py": "Call(Attribute({self}, setOff), [directLight])"}, "out": ["Next", "value"], "in": [{"name": "Call", "type": "In"}, {"name": "self", "type": "In"}, {"name": "directLight", "type": "In"}]}}}