{"Nodes": {"LineNodePath___init__": {"name": "LineNodePath", "cat": "Panda3D,direct,LineNodePath", "extraAttr": {"py": "Call(Attribute({self}, LineNodePath), [parent,name,thickness,colorVec])"}, "out": ["Next", "value"], "in": [{"name": "Call", "type": "In"}, {"name": "self", "type": "In"}, {"name": "parent", "type": "In"}, {"name": "name", "type": "In"}, {"name": "thickness", "type": "In"}, {"name": "colorVec", "type": "In"}]}, "LineNodePath_moveTo": {"name": "moveTo", "cat": "Panda3D,direct,LineNodePath", "extraAttr": {"py": "Call(Attribute({self}, moveTo), [__x,__y,__z])"}, "out": ["Next", "value"], "in": [{"name": "Call", "type": "In"}, {"name": "self", "type": "In"}, {"name": "__x", "type": "In"}, {"name": "__y", "type": "In"}, {"name": "__z", "type": "In"}]}, "LineNodePath_drawTo": {"name": "drawTo", "cat": "Panda3D,direct,LineNodePath", "extraAttr": {"py": "Call(Attribute({self}, drawTo), [__x,__y,__z])"}, "out": ["Next", "value"], "in": [{"name": "Call", "type": "In"}, {"name": "self", "type": "In"}, {"name": "__x", "type": "In"}, {"name": "__y", "type": "In"}, {"name": "__z", "type": "In"}]}, "LineNodePath_create": {"name": "create", "cat": "Panda3D,direct,LineNodePath", "extraAttr": {"py": "Call(Attribute({self}, create), [frameAccurate])"}, "out": ["Next", "value"], "in": [{"name": "Call", "type": "In"}, {"name": "self", "type": "In"}, {"name": "frameAccurate", "type": "In"}]}, "LineNodePath_reset": {"name": "reset", "cat": "Panda3D,direct,LineNodePath", "extraAttr": {"py": "Call(Attribute({self}, reset), [])"}, "out": ["Next", "value"], "in": [{"name": "Call", "type": "In"}, {"name": "self", "type": "In"}]}, "LineNodePath_isEmpty": {"name": "isEmpty", "cat": "Panda3D,direct,LineNodePath", "extraAttr": {"py": "Call(Attribute({self}, isEmpty), [])"}, "out": ["Next", "value"], "in": [{"name": "Call", "type": "In"}, {"name": "self", "type": "In"}]}, "LineNodePath_setThickness": {"name": "setThickness", "cat": "Panda3D,direct,LineNodePath", "extraAttr": {"py": "Call(Attribute({self}, setThickness), [thickness])"}, "out": ["Next", "value"], "in": [{"name": "Call", "type": "In"}, {"name": "self", "type": "In"}, {"name": "thickness", "type": "In"}]}, "LineNodePath_setColor": {"name": "setColor", "cat": "Panda3D,direct,LineNodePath", "extraAttr": {"py": "Call(Attribute({self}, setColor), [__r,__g,__b,__a])"}, "out": ["Next", "value"], "in": [{"name": "Call", "type": "In"}, {"name": "self", "type": "In"}, {"name": "__r", "type": "In"}, {"name": "__g", "type": "In"}, {"name": "__b", "type": "In"}, {"name": "__a", "type": "In"}]}, "LineNodePath_setVertex": {"name": "setVertex", "cat": "Panda3D,direct,LineNodePath", "extraAttr": {"py": "Call(Attribute({self}, setVertex), [__vertex,__x,__y,__z])"}, "out": ["Next", "value"], "in": [{"name": "Call", "type": "In"}, {"name": "self", "type": "In"}, {"name": "__vertex", "type": "In"}, {"name": "__x", "type": "In"}, {"name": "__y", "type": "In"}, {"name": "__z", "type": "In"}]}, "LineNodePath_setVertexColor": {"name": "setVertexColor", "cat": "Panda3D,direct,LineNodePath", "extraAttr": {"py": "Call(Attribute({self}, setVertexColor), [vertex,__r,__g,__b,__a])"}, "out": ["Next", "value"], "in": [{"name": "Call", "type": "In"}, {"name": "self", "type": "In"}, {"name": "vertex", "type": "In"}, {"name": "__r", "type": "In"}, {"name": "__g", "type": "In"}, {"name": "__b", "type": "In"}, {"name": "__a", "type": "In"}]}, "LineNodePath_getCurrentPosition": {"name": "getCurrentPosition", "cat": "Panda3D,direct,LineNodePath", "extraAttr": {"py": "Call(Attribute({self}, getCurrentPosition), [])"}, "out": ["Next", "value"], "in": [{"name": "Call", "type": "In"}, {"name": "self", "type": "In"}]}, "LineNodePath_getNumVertices": {"name": "getNumVertices", "cat": "Panda3D,direct,LineNodePath", "extraAttr": {"py": "Call(Attribute({self}, getNumVertices), [])"}, "out": ["Next", "value"], "in": [{"name": "Call", "type": "In"}, {"name": "self", "type": "In"}]}, "LineNodePath_getVertex": {"name": "getVertex", "cat": "Panda3D,direct,LineNodePath", "extraAttr": {"py": "Call(Attribute({self}, getVertex), [index])"}, "out": ["Next", "value"], "in": [{"name": "Call", "type": "In"}, {"name": "self", "type": "In"}, {"name": "index", "type": "In"}]}, "LineNodePath_getVertexColor": {"name": "getVertexColor", "cat": "Panda3D,direct,LineNodePath", "extraAttr": {"py": "Call(Attribute({self}, getVertexColor), [])"}, "out": ["Next", "value"], "in": [{"name": "Call", "type": "In"}, {"name": "self", "type": "In"}]}, "LineNodePath_drawArrow": {"name": "drawArrow", "cat": "Panda3D,direct,LineNodePath", "extraAttr": {"py": "Call(Attribute({self}, drawArrow), [sv,ev,arrowAngle,arrowLength])"}, "out": ["Next", "value"], "in": [{"name": "Call", "type": "In"}, {"name": "self", "type": "In"}, {"name": "sv", "type": "In"}, {"name": "ev", "type": "In"}, {"name": "arrowAngle", "type": "In"}, {"name": "arrowLength", "type": "In"}]}, "LineNodePath_drawArrow2d": {"name": "drawArrow2d", "cat": "Panda3D,direct,LineNodePath", "extraAttr": {"py": "Call(Attribute({self}, drawArrow2d), [sv,ev,arrowAngle,arrowLength])"}, "out": ["Next", "value"], "in": [{"name": "Call", "type": "In"}, {"name": "self", "type": "In"}, {"name": "sv", "type": "In"}, {"name": "ev", "type": "In"}, {"name": "arrowAngle", "type": "In"}, {"name": "arrowLength", "type": "In"}]}, "LineNodePath_drawLines": {"name": "drawLines", "cat": "Panda3D,direct,LineNodePath", "extraAttr": {"py": "Call(Attribute({self}, drawLines), [lineList])"}, "out": ["Next", "value"], "in": [{"name": "Call", "type": "In"}, {"name": "self", "type": "In"}, {"name": "lineList", "type": "In"}]}, "planeIntersect": {"name": "planeIntersect", "cat": "Panda3D,direct", "extraAttr": {"py": ["Call(planeIntersect, [lineOrigin,lineDir,planeOrigin,normal])"]}, "out": ["Next", "value"], "in": [{"name": "Call", "type": "In"}, {"name": "lineOrigin", "type": "In"}, {"name": "lineDir", "type": "In"}, {"name": "planeOrigin", "type": "In"}, {"name": "normal", "type": "In"}]}, "getNearProjectionPoint": {"name": "getNearProjectionPoint", "cat": "Panda3D,direct", "extraAttr": {"py": ["Call(getNearProjectionPoint, [nodePath])"]}, "out": ["Next", "value"], "in": [{"name": "Call", "type": "In"}, {"name": "nodePath", "type": "In"}]}, "getScreenXY": {"name": "getScreenXY", "cat": "Panda3D,direct", "extraAttr": {"py": ["Call(getScreenXY, [nodePath])"]}, "out": ["Next", "value"], "in": [{"name": "Call", "type": "In"}, {"name": "nodePath", "type": "In"}]}, "getCrankAngle": {"name": "getCrankAngle", "cat": "Panda3D,direct", "extraAttr": {"py": ["Call(getCrankAngle, [center])"]}, "out": ["Next", "value"], "in": [{"name": "Call", "type": "In"}, {"name": "center", "type": "In"}]}, "relHpr": {"name": "relHpr", "cat": "Panda3D,direct", "extraAttr": {"py": ["Call(relHpr, [nodePath,base,h,p,r])"]}, "out": ["Next", "value"], "in": [{"name": "Call", "type": "In"}, {"name": "nodePath", "type": "In"}, {"name": "base", "type": "In"}, {"name": "h", "type": "In"}, {"name": "p", "type": "In"}, {"name": "r", "type": "In"}]}, "qSlerp": {"name": "qSlerp", "cat": "Panda3D,direct", "extraAttr": {"py": ["Call(qSlerp, [startQuat,endQuat,t])"]}, "out": ["Next", "value"], "in": [{"name": "Call", "type": "In"}, {"name": "startQuat", "type": "In"}, {"name": "endQuat", "type": "In"}, {"name": "t", "type": "In"}]}}}