{"Nodes": {"DirectCheckButton___init__": {"name": "DirectCheckButton", "cat": "Panda3D,direct,DirectCheckButton", "extraAttr": {"py": "Call(Attribute({self}, DirectCheckButton), [parent])"}, "out": ["Next", "value"], "in": [{"name": "Call", "type": "In"}, {"name": "self", "type": "In"}, {"name": "parent", "type": "In"}]}, "DirectCheckButton_setIndicatorValue": {"name": "setIndicatorValue", "cat": "Panda3D,direct,DirectCheckButton", "extraAttr": {"py": "Call(Attribute({self}, setIndicatorValue), [])"}, "out": ["Next", "value"], "in": [{"name": "Call", "type": "In"}, {"name": "self", "type": "In"}]}}}